{
  "presence.activity.browsing": {
    "description": "Shows when you hover over the little magnifying glass icon at your Discord Rich Presence",
    "message": "Đang duyệt..."
  },
  "presence.activity.live": {
    "description": "Shows when you hover over the little red circle icon at your Discord Rich Presence",
    "message": "Trực tiếp"
  },
  "presence.activity.reading": {
    "description": "Shows when you hover over the little icon at your Discord Rich Presence",
    "message": "Đang đọc"
  },
  "presence.activity.searching": {
    "description": "Shows when you hover over the little icon at your Discord Rich Presence",
    "message": "Đang tìm kiếm"
  },
  "presence.media.info.episode": {
    "description": "Shows the current episode at your Discord Rich Presence; {0} will be replaced -> is a variable and should not be translated",
    "message": "Tập {0}"
  },
  "presence.playback.paused": {
    "description": "Shows when you hover over the little paused icon at your Discord Rich Presence",
    "message": "Tạm ngưng phát lại"
  },
  "presence.playback.playing": {
    "description": "Shows when you hover over the little play icon at your Discord Rich Presence",
    "message": "Phát lại"
  }
}
