{
	"downloads.header.title": {
		"message": "Время показа выключено.",
		"description": "Title"
	},
	"downloads.header.subtitle": {
		"message": "Используйте PreMiD сейчас и покажите своим друзьям, что вы смотрите или слушаете, может быть вы найдете кого-нибудь со схожими интересами.",
		"description": "Subtitle for header"
	},
	"downloads.instructions.heading": {
		"message": "Начало работы",
		"description": "Displayed at Downloads page above steps"
	},
	"downloads.instructions.step_1": {
		"message": "Скачать PreMiD",
		"description": "Heading for installing the application"
	},
	"downloads.instructions.step_2": {
		"message": "Установить приложение",
		"description": "Heading for installing the application"
	},
	"downloads.instructions.step_3": {
		"message": "Добавить расширение в свой браузера",
		"description": "Heading for installing the application"
	},
	"downloads.appdownloading.header": {
		"message": "Скачать приложение",
		"description": "Header above application download buttons."
	},
	"downloads.extdownloading.header": {
		"message": "Установить расширение",
		"description": "Header above extension download buttons."
	},
	"downloads.tooltips.os_not_supported.part2": {
		"message": "{0} Приложение не имеет установщика для этой операционной системы. Это означает, что для неё не будет квалифицированной поддержки.",
		"description": "Next part of the tooltip message. {0} are replaced with `downloads.tooltips.os_not_supported.part1`"
	},
	"downloads.mobile.showDownloads": {
		"message": "Показать загрузки",
		"description": "Little button on the downloads page for mobile users."
	},
	"downloads.mobile.hideDownloads": {
		"message": "Спрятать загрузки",
		"description": "Little button on the downloads page for mobile users."
	},
	"downloads.error.noaccess.title": {
		"message": "Кажется, у вас нет доступа к альфа/бета версии :(",
		"description": "Error message if the user doesn't alpha/beta access."
	},
	"downloads.button.cancel": {
		"message": "Отменить",
		"description": "Button on the modal of Opera/Edge browsers."
	},
	"downloads.button.done": {
		"message": "Готово",
		"description": "Button on the page when trying to download with adblocker on."
	},
	"downloads.adsbox.thankyou.title": {
		"message": "Благодарим вас!",
		"description": "Title of the advertisement section box."
	}
}
