{
  "premid.docs": {
    "description": "as in documents",
    "message": "Documentação"
  },
  "premid.pageAbout": {
    "description": "A page name",
    "message": "Sobre o PreMiD"
  },
  "premid.pageApi": {
    "description": "A page name",
    "message": "API"
  },
  "premid.pageApiVersion": {
    "description": "A page name // {0} will be replaced with the version number.",
    "message": "Entendendo a API v{0}"
  },
  "premid.pageContributors": {
    "description": "A page name",
    "message": "Contribuidores"
  },
  "premid.pageDownloads": {
    "description": "A page name",
    "message": "Downloads"
  },
  "premid.pageHome": {
    "description": "A page name",
    "message": "Página inicial"
  },
  "premid.pageIframe": {
    "description": "A page name",
    "message": "Entendendo o iframe"
  },
  "premid.pageInstall": {
    "description": "A page name",
    "message": "Instalação"
  },
  "premid.pageInstallFor": {
    "description": "A page name // {0} will be replaced with Windows, Linux, Chrome etc.",
    "message": "Assistente de instalação para {0}"
  },
  "premid.pageMetadata": {
    "description": "A page name",
    "message": "Configurando metadata.json"
  },
  "premid.pagePresenceClass": {
    "description": "A page name",
    "message": "Classe Presence"
  },
  "premid.pagePresenceDev": {
    "description": "A page name",
    "message": "Desenvolvimento de presences"
  },
  "premid.pagePresenceGuide": {
    "description": "A page name",
    "message": "Diretrizes de Presences"
  },
  "premid.pageSlideshowClass": {
    "description": "A page name",
    "message": "Classe de Slideshow"
  },
  "premid.pageStart": {
    "description": "A page name",
    "message": "Primeiros passos"
  },
  "premid.pageStore": {
    "description": "A page name",
    "message": "Loja"
  },
  "premid.pageSysReq": {
    "description": "A page name",
    "message": "Requisitos de sistema"
  },
  "premid.pageTroubleshooting": {
    "description": "A page name",
    "message": "Solução de problemas"
  },
  "premid.pageTs": {
    "description": "A page name",
    "message": "Configurando TypeScript"
  },
  "premid.partners": {
    "description": "A page name",
    "message": "Parceiros"
  },
  "premid.viewPage": {
    "description": "",
    "message": "Vendo a página:"
  },
  "premid.viewPresence": {
    "description": "",
    "message": "Vendo a presence:"
  }
}
