{
  "presence.page.buttons.sourceCode": {
    "description": "Source Code button on presence pages.",
    "message": "Code source"
  },
  "presence.sections.changelog.title": {
    "description": "The title of the changelog section.",
    "message": "Journal de modifications"
  },
  "presence.sections.description.title": {
    "description": "The title of the description section.",
    "message": "Description"
  },
  "presence.sections.information.author": {
    "description": "One of the strings from the Information section. [on webite -> Author: (username)]",
    "message": "Auteur"
  },
  "presence.sections.information.contributors": {
    "description": "One of the strings from the Information section. [on webite -> Contributors: (array)]",
    "message": "Contributeurs"
  },
  "presence.sections.information.likes": {
    "description": "One of the strings from the Information section. [on webite -> Likes: (56)]",
    "message": "J'aimes"
  },
  "presence.sections.information.moreurls": {
    "description": "Shown in a presence’s page if it uses RegExp. The term \"RegExp\" should not be translated",
    "message": "Cette Presence prend en charge plus d'URLs que celles listées ci-dessous grâce à l'utilisation de RegExp. Survolez pour voir le modèle"
  },
  "presence.sections.information.supportedurls": {
    "description": "One of the strings from the Information section. [on webite -> Supported URLs: (array)]",
    "message": "URL supportées"
  },
  "presence.sections.information.tags": {
    "description": "One of the strings from the Information section. [on webite -> Tags: (tag) (tag) (tag)]",
    "message": "Tags"
  },
  "presence.sections.information.title": {
    "description": "The title of the information section.",
    "message": "Information"
  },
  "presence.sections.information.users": {
    "description": "One of the strings from the Information section. [on webite -> Users: (2000)]",
    "message": "Utilisateurs"
  },
  "presence.sections.information.version": {
    "description": "One of the strings from the Information section. [on webite -> Version: (2.0)]",
    "message": "Version"
  }
}
