{
  "header.language": {
    "message": "Dansk",
    "description": "Replace English with the name of YOUR language!"
  },
  "header.languageNotification.title": {
    "message": "Vi understytter dit sprog. Vil du skifte?",
    "description": "Heading of the language notification when user has different language."
  },
  "header.languageNotification.text": {
    "message": "Vores hjemmeside er blevet oversat til dit sprog. Det her kan meget vel hjælpe dig, i tilfælde af at du ikke snakker engelsk særligt godt.",
    "description": "Text in language notification when user has different language."
  },
  "header.languageNotification.btnDecline": {
    "message": "Nej tak",
    "description": "Button that will decline notification."
  },
  "header.languageNotification.btnAccept": {
    "message": "Skift sprog",
    "description": "Button that switches language after click."
  },
  "header.loader.phrases": {
    "message": "Bager pandekager...;Kigger på Beholdere...;Analyserer din IP adresse...;UwU;Bryder regler...",
    "description": "Randomly appears when website is loading data. [WARNING: Keep the `;` symbol, it's used to separate phrases]"
  },
  "header.store": {
    "message": "Butik",
    "description": "Store tab"
  },
  "header.downloads": {
    "message": "Installationer",
    "description": "Downloads tab"
  },
  "header.contributors": {
    "message": "Bidragere",
    "description": "Contributors tab"
  }
}
