{
  "downloads.header.title": {
    "message": "Es hora de que te muestres a todos.",
    "description": "Title"
  },
  "downloads.header.subtitle": {
    "message": "Empieza a usar PreMiD ahora y muestra a otras personas lo que estás haciendo, tal vez encuentres a alguien con los mismos intereses.",
    "description": "Subtitle for header"
  },
  "downloads.instructions.heading": {
    "message": "Empecemos",
    "description": "Displayed at Downloads page above steps"
  },
  "downloads.instructions.step_1": {
    "message": "Descargar PreMiD.",
    "description": "Heading for installing the application"
  },
  "downloads.instructions.step_2": {
    "message": "Instalar la aplicación PreMiD.",
    "description": "Heading for installing the application"
  },
  "downloads.instructions.step_3": {
    "message": "Instala la extensión para tu navegador.",
    "description": "Heading for installing the application"
  },
  "downloads.instructions.step_4": {
    "message": "Visita la página {0} y comprueba si la extensión está conectada.",
    "description": "{0} will be replaced by 'store' string translation"
  },
  "downloads.instructions.step_4_store": {
    "message": "tienda",
    "description": "Be sure that you understand the context! This string will be included in `downloads.instructions.step_4` instead of {0}"
  },
  "downloads.appdownloading.header": {
    "message": "Aplicación",
    "description": "Header above application download buttons."
  },
  "downloads.extdownloading.header": {
    "message": "Extensión",
    "description": "Header above extension download buttons."
  },
  "downloads.tooltips.os_not_supported.part1": {
    "message": "ADVERTENCIA:",
    "description": "First part of the message."
  },
  "downloads.tooltips.os_not_supported.part2": {
    "message": "{0} No hay instalador para este sistema operativo. Esto quiere decir que no hay soporte profesional para él.",
    "description": "Next part of the tooltip message. {0} are replaced with `downloads.tooltips.os_not_supported.part1`"
  }
}
