{
  "gmail.categoryPrimary": {
    "message": "Bekijkt categorie Primair",
    "description": "Displayed when viewing emails in the primary category."
  },
  "gmail.categorySocial": {
    "message": "Bekijkt categorie Sociaal",
    "description": "Displayed when viewing emails in the social category."
  },
  "gmail.categoryUpdates": {
    "message": "Bekijkt categorie Updates",
    "description": "Displayed when viewing emails in the updates category."
  },
  "gmail.categoryPromotions": {
    "message": "Bekijkt categorie Reclame",
    "description": "Displayed when viewing emails in the promotions category."
  },
  "gmail.categoryForum": {
    "message": "Bekijkt categorie Forums",
    "description": "Displayed when viewing emails in the forums category."
  },
  "gmail.inLabel": {
    "message": "Bekijkt label",
    "description": "Displayed when a user is browsing emails in a certain label. The name of the label will appear below."
  },
  "gmail.generalSettings": {
    "message": "Past algemene instellingen aan",
    "description": "Displayed when the user is modifying their settings"
  },
  "gmail.labelSettings": {
    "message": "Past labelinstellingen aan",
    "description": "Displayed when the user is modifying their labels"
  },
  "gmail.inboxSettings": {
    "message": "Past inboxinstellingen aan",
    "description": "Displayed when the user is modifying their inbox settings"
  },
  "gmail.accountSetting": {
    "message": "Past account-/importinstellingen aan",
    "description": "Displayed when the user is modifying their account's settings"
  },
  "gmail.filterSettings": {
    "message": "Past filters en geblokkeerde adressen aan",
    "description": "Displayed when the user is modifying their filters and blocked addresses"
  },
  "gmail.fwdAndPOPSettings": {
    "message": "Past doorstuur-/POP-/IMAP-instellingen aan",
    "description": "Displayed when the user is modifying their forwarding, POP and IMAP settings"
  },
  "gmail.addonsSettings": {
    "message": "Past add-ons aan",
    "description": "Displayed when the user is modifying their add-ons"
  },
  "gmail.chatSettings": {
    "message": "Past 'meet en chatten'-instellingen aan",
    "description": "Displayed when the user is modifying their chat settings"
  },
  "gmail.advancedSettings": {
    "message": "Past geavanceerde instellingen aan",
    "description": "Displayed when the user is modifying their advanced settings"
  },
  "gmail.offlineSettings": {
    "message": "Past offline-instellingen aan",
    "description": "Displayed when the user is modifying their offline settings"
  },
  "gmail.themesSettings": {
    "message": "Kiest een thema uit",
    "description": "Displayed when the user is modifying their theme in the settings"
  },
  "gmail.lookingForEmail": {
    "message": "Zoekt naar een e-mail",
    "description": "Displayed when the user is searching for an email"
  },
  "gmail.viewingEmail": {
    "message": "Bekijkt een e-mail",
    "description": "Displayed when the user is viewing an email"
  },
  "gmail.viewingStarredEmails": {
    "message": "Bekijkt e-mails met ster",
    "description": "Displayed when the user is viewing emails marked with a star"
  },
  "gmail.viewingSentEmails": {
    "message": "Bekijkt verzonden e-mails",
    "description": "Displayed when the user is viewing the emails they have sent"
  },
  "gmail.viewingSnoozedEmails": {
    "message": "Bekijkt gesluimerde e-mails",
    "description": "Displayed when the user is viewing their snoozed emails"
  },
  "gmail.viewingDrafts": {
    "message": "Bekijkt concepten",
    "description": "Displayed when the user is viewing their drafts"
  },
  "gmail.viewingImportantEmails": {
    "message": "Bekijkt belangrijke e-mails",
    "description": "Displayed when the user is viewing emails marked as important"
  },
  "gmail.viewingTrash": {
    "message": "Bekijkt prullenbak",
    "description": "Displayed when the user is viewing their trash"
  },
  "gmail.viewingChats": {
    "message": "Bekijkt chats",
    "description": "Displayed when the user is viewing their chats"
  },
  "gmail.viewingScheduled": {
    "message": "Bekijkt geplande e-mails",
    "description": "Displayed when the user is viewing their scheduled emails"
  },
  "gmail.viewingSpam": {
    "message": "Bekijkt spam",
    "description": "Displayed when the user is viewing their spam"
  },
  "gmail.viewingAllEmails": {
    "message": "Bekijkt alle e-mails",
    "description": "Displayed when the user is viewing all their emails"
  },
  "gmail.composingEmail": {
    "message": "Stelt een e-mail op",
    "description": "Displayed when the user is composing an email"
  }
}
