{
  "contributors.headings.staff": {
    "message": "Administracja",
    "description": "Heading for group of users."
  },
  "contributors.headings.supporters": {
    "message": "Wspierający",
    "description": "Heading for group of users."
  },
  "contributors.headings.translators": {
    "message": "Tłumacze",
    "description": "Heading for group of users."
  },
  "contributors.roles.mainDeveloper": {
    "message": "Główny programista",
    "description": "'Main Developer' title for contributors and user pages."
  },
  "contributors.roles.websiteDeveloper": {
    "message": "Twórcy strony internetowej",
    "description": "'Website Developer' title for contributors and user pages."
  },
  "contributors.roles.communityManager": {
    "message": "Community Manager",
    "description": "'Community Manager' title for contributors and user pages."
  },
  "contributors.roles.headModerator": {
    "message": "Główny moderator",
    "description": "'Head Moderator' title for contributors and user pages."
  },
  "contributors.roles.moderator": {
    "message": "Moderator",
    "description": "'Moderator' title for contributors and user pages."
  },
  "contributors.roles.ticketManager": {
    "message": "Menedżer zgłoszeń",
    "description": "'Ticket Manager' title for contributors and user pages."
  },
  "contributors.roles.donator": {
    "message": "Donator",
    "description": "'Donator' title for contributors page."
  },
  "contributors.roles.booster": {
    "message": "Booster",
    "description": "'Booster' title for contributors page and user pages."
  },
  "contributors.roles.translator": {
    "message": "Tłumacz",
    "description": "'Main Developer' title for contributors page."
  }
}
