{
  "animepahe.loading": {
    "message": "loading",
    "description": ""
  },
  "animepahe.browsing": {
    "message": "Browsing",
    "description": "part"
  },
  "animepahe.browsingHome": {
    "message": "Latest Releases",
    "description": ""
  },
  "animepahe.browsingAll": {
    "message": "A-Z",
    "description": ""
  },
  "animepahe.browsingGenre": {
    "message": "Genre",
    "description": ""
  },
  "animepahe.browsingSeason": {
    "message": "Season",
    "description": "TV show/series season eg. Season 5 of The Flash"
  },
  "animepahe.browsingSpecial": {
    "message": "Special",
    "description": ""
  },
  "animepahe.view": {
    "message": "View on",
    "description": "followed by Pahe/AniList"
  },
  "animepahe.watch": {
    "message": "Watch",
    "description": "followed by Movie or episode"
  },
  "animepahe.watching": {
    "message": "Watching",
    "description": "followed by Movie or episode"
  },
  "animepahe.movie": {
    "message": "Movie",
    "description": ""
  },
  "animepahe.episode": {
    "message": "episode",
    "description": ""
  },
  "animepahe.timeSeason": {
    "message": "Season",
    "description": "Time Season eg. The season is now Winter"
  }
} 
